flask_scenario_testing/__init__.py
flask_scenario_testing/analysis/CpuBucket.py
flask_scenario_testing/analysis/Results.py
flask_scenario_testing/analysis/Scenario.py
flask_scenario_testing/analysis/__init__.py
flask_scenario_testing/analysis/main.py
flask_scenario_testing/analysis/report_sections/EndpointOverview.py
flask_scenario_testing/analysis/report_sections/MedianLatency.py
flask_scenario_testing/analysis/report_sections/PlotCpuUsageAgainstLatency.py
flask_scenario_testing/analysis/report_sections/PlotCpuUsageOverTime.py
flask_scenario_testing/analysis/report_sections/PlotLatenciesOverTime.py
flask_scenario_testing/analysis/report_sections/PlotTransactionSignatures.py
flask_scenario_testing/analysis/report_sections/ReportSection.py
flask_scenario_testing/analysis/report_sections/SimulationDetails.py
flask_scenario_testing/analysis/report_sections/__init__.py
flask_scenario_testing/analysis/segmenters/RollingSegmenter.py
flask_scenario_testing/analysis/segmenters/Segmenter.py
flask_scenario_testing/analysis/segmenters/TimeWindowedSegmenter.py
flask_scenario_testing/analysis/segmenters/__init__.py
flask_scenario_testing/analysis/services/ComputeCpuUsageAgainstLatency.py
flask_scenario_testing/analysis/services/ComputeCpuUsageOverTime.py
flask_scenario_testing/analysis/services/ComputeTransactionSignature.py
flask_scenario_testing/analysis/services/__init__.py
flask_scenario_testing/analysis/support/Averager.py
flask_scenario_testing/analysis/support/Measurement.py
flask_scenario_testing/analysis/support/MeasurementsSegment.py
flask_scenario_testing/analysis/support/ServiceTime.py
flask_scenario_testing/analysis/support/__init__.py
flask_scenario_testing/backend/Simulation.py
flask_scenario_testing/backend/initialise_scenario_testing.py
flask_scenario_testing/backend/views.py
flask_scenario_testing/backend/modifiers/BusySleep.py
flask_scenario_testing/backend/modifiers/Fibonacci.py
flask_scenario_testing/backend/modifiers/Modifier.py
flask_scenario_testing-1.0.14.dist-info/METADATA
flask_scenario_testing-1.0.14.dist-info/WHEEL
flask_scenario_testing-1.0.14.dist-info/top_level.txt
flask_scenario_testing-1.0.14.dist-info/RECORD
